vnpy_jotdx/__init__.py
vnpy_jotdx/datafeed.py
vnpy_jotdx-0.1.8.dist-info/WHEEL
vnpy_jotdx-0.1.8.dist-info/METADATA
vnpy_jotdx-0.1.8.dist-info/RECORD
